mofax/__init__.py
mofax/core.py
mofax/plot.py
mofax/plot_data.py
mofax/plot_factors.py
mofax/plot_mefisto.py
mofax/plot_utils.py
mofax/plot_variance.py
mofax/plot_weights.py
mofax/utils.py
mofax-0.3.7.dist-info/LICENSE
mofax-0.3.7.dist-info/METADATA
mofax-0.3.7.dist-info/WHEEL
mofax-0.3.7.dist-info/RECORD
