Metadata-Version: 2.1
Name: mofax
Version: 0.3.7
Summary: Work with MOFA+ models in Python
Author: Danila Bredikhin
Author-email: danila.bredikhin@embl.de
Requires-Python: >=3.7
Classifier: Programming Language :: Python :: 3
Classifier: Programming Language :: Python :: 3.7
Classifier: Programming Language :: Python :: 3.8
Classifier: Programming Language :: Python :: 3.9
Classifier: Programming Language :: Python :: 3.10
Classifier: Programming Language :: Python :: 3.11
Classifier: Programming Language :: Python :: 3.12
Classifier: Programming Language :: Python :: 3.13
Requires-Dist: h5py (>=2.9.0)
Requires-Dist: matplotlib (>=3.1.0)
Requires-Dist: numpy (>=1.17.0)
Requires-Dist: pandas (>=1.0.0)
Requires-Dist: scipy
Requires-Dist: seaborn (>=0.9.0)
